praxis/__init__.py
tests/__init__.py
praxis_ml-0.1.0.dist-info/LICENSE
praxis_ml-0.1.0.dist-info/METADATA
praxis_ml-0.1.0.dist-info/WHEEL
praxis_ml-0.1.0.dist-info/top_level.txt
praxis_ml-0.1.0.dist-info/RECORD
